PT_FT_classification/LICENSE
PT_FT_classification/README.md
PT_FT_classification/__init__.py
PT_FT_classification/configs/Raw/Crop_res50_plain_082723.yaml
PT_FT_classification/data/imgs/10050028_0.JPG
PT_FT_classification/data/imgs/10050028_1.JPG
PT_FT_classification/data/imgs/10050028_2.JPG
PT_FT_classification/data/imgs/10050028_3.JPG
PT_FT_classification/data/imgs/10050028_4.JPG
PT_FT_classification/data/imgs/10050028_5.JPG
PT_FT_classification/data/imgs/10050028_6.JPG
PT_FT_classification/data/imgs/10050028_7.JPG
PT_FT_classification/data/imgs/10050028_8.JPG
PT_FT_classification/data/imgs/10050028_9.JPG
PT_FT_classification/data/imgs/annotation_example.csv
PT_FT_classification/environment.yaml
PT_FT_classification/main.py
PT_FT_classification/requirements.txt
PT_FT_classification/src/algorithms/__init__.py
PT_FT_classification/src/algorithms/plain.py
PT_FT_classification/src/algorithms/utils.py
PT_FT_classification/src/datasets/__init__.py
PT_FT_classification/src/datasets/custom.py
PT_FT_classification/src/models/__init__.py
PT_FT_classification/src/models/plain_resnet.py
PT_FT_classification/src/utils/__init__.py
PT_FT_classification/src/utils/batch_detection_cropping.py
PT_FT_classification/src/utils/data_splitting.py
PT_FT_classification/src/utils/utils.py
PytorchWildlife/__init__.py
PytorchWildlife/cli.py
PytorchWildlife/data/__init__.py
PytorchWildlife/data/datasets.py
PytorchWildlife/data/transforms.py
PytorchWildlife/models/__init__.py
PytorchWildlife/models/classification/__init__.py
PytorchWildlife/models/classification/resnet/__init__.py
PytorchWildlife/models/classification/resnet/amazon.py
PytorchWildlife/models/classification/resnet/base_classifier.py
PytorchWildlife/models/classification/resnet/opossum.py
PytorchWildlife/models/classification/resnet/serengeti.py
PytorchWildlife/models/detection/__init__.py
PytorchWildlife/models/detection/yolov5/__init__.py
PytorchWildlife/models/detection/yolov5/base_detector.py
animalsearch-0.0.4.dist-info/entry_points.txt
animalsearch-0.0.4.dist-info/WHEEL
animalsearch-0.0.4.dist-info/METADATA
animalsearch-0.0.4.dist-info/licenses/LICENSE
animalsearch-0.0.4.dist-info/RECORD
