Metadata-Version: 2.1
Name: animalsearch
Version: 0.0.4
Summary: A CLI for sorting animal images.
License: MIT
Author: Tim Cogan
Requires-Python: >=3.10
Requires-Dist: Pillow
Requires-Dist: colorama
Requires-Dist: gradio
Requires-Dist: numpy
Requires-Dist: opencv-python
Requires-Dist: supervision
Requires-Dist: torch
Requires-Dist: torchaudio
Requires-Dist: torchvision
Requires-Dist: tqdm
Requires-Dist: ultralytics-yolov5
